portpilot/__init__.py
portpilot/app.py
portpilot/cli.py
portpilot-0.1.3.dist-info/licenses/LICENSE
portpilot-0.1.3.dist-info/METADATA
portpilot-0.1.3.dist-info/WHEEL
portpilot-0.1.3.dist-info/entry_points.txt
portpilot-0.1.3.dist-info/top_level.txt
portpilot-0.1.3.dist-info/RECORD
