Metadata-Version: 2.4
Name: portpilot
Version: 0.1.3
Summary: Interactive terminal port manager for developers
Author: Emre Çalışkan
License: MIT
Project-URL: Homepage, https://github.com/cyber-emreclskn/portpilot
Project-URL: Documentation, https://github.com/cyber-emreclskn/portpilot#readme
Project-URL: Repository, https://github.com/cyber-emreclskn/portpilot
Project-URL: Issues, https://github.com/cyber-emreclskn/portpilot/issues
Project-URL: Changelog, https://github.com/cyber-emreclskn/portpilot/releases
Keywords: port,process,terminal,tui,developer,tools,kill,network
Classifier: Development Status :: 4 - Beta
Classifier: Environment :: Console
Classifier: Intended Audience :: Developers
Classifier: License :: OSI Approved :: MIT License
Classifier: Operating System :: POSIX :: Linux
Classifier: Operating System :: MacOS
Classifier: Programming Language :: Python :: 3
Classifier: Programming Language :: Python :: 3.8
Classifier: Programming Language :: Python :: 3.9
Classifier: Programming Language :: Python :: 3.10
Classifier: Programming Language :: Python :: 3.11
Classifier: Programming Language :: Python :: 3.12
Classifier: Topic :: System :: Systems Administration
Classifier: Topic :: Utilities
Requires-Python: >=3.8
License-File: LICENSE
Requires-Dist: textual>=0.40.0
Requires-Dist: rich>=13.0.0
Requires-Dist: click>=8.0.0
Requires-Dist: psutil>=5.9.0
Provides-Extra: dev
Requires-Dist: pytest>=7.0.0; extra == "dev"
Requires-Dist: pytest-cov>=4.0.0; extra == "dev"
Requires-Dist: black>=23.0.0; extra == "dev"
Requires-Dist: ruff>=0.1.0; extra == "dev"
Dynamic: license-file
